polerisk/__init__.py
polerisk/core.py
polerisk-1.1.0.dist-info/licenses/LICENSE
soilmoisture/__init__.py
soilmoisture/acceleration/__init__.py
soilmoisture/acceleration/numba_ops.py
soilmoisture/advanced/__init__.py
soilmoisture/advanced/climatology.py
soilmoisture/advanced/time_series.py
soilmoisture/analysis/__init__.py
soilmoisture/analysis/analyze_results.py
soilmoisture/analysis/statistics.py
soilmoisture/cloud/__init__.py
soilmoisture/cloud/aws_integration.py
soilmoisture/common/__init__.py
soilmoisture/common/config.py
soilmoisture/common/data_loader.py
soilmoisture/core/__init__.py
soilmoisture/core/getlocation.py
soilmoisture/core/getlprm_des.py
soilmoisture/core/lprm_utils.py
soilmoisture/core/match_insitu_with_lprm.py
soilmoisture/core/matching.py
soilmoisture/core/parameters.py
soilmoisture/core/utc2local.py
soilmoisture/data/__init__.py
soilmoisture/data_sources/__init__.py
soilmoisture/data_sources/smap_processor.py
soilmoisture/database/__init__.py
soilmoisture/database/models.py
soilmoisture/ml/__init__.py
soilmoisture/ml/cli.py
soilmoisture/ml/features.py
soilmoisture/ml/models.py
soilmoisture/pipeline/__init__.py
soilmoisture/pipeline/data_ingestion.py
soilmoisture/pole_health/__init__.py
soilmoisture/pole_health/assessment.py
soilmoisture/pole_health/enhanced_models.py
soilmoisture/pole_health/pole_data.py
soilmoisture/pole_health/risk_scoring.py
soilmoisture/pole_health/structural_assessment.py
soilmoisture/tests/__init__.py
soilmoisture/tests/conftest.py
soilmoisture/tests/test_advanced.py
soilmoisture/tests/test_analysis.py
soilmoisture/tests/test_geo_utils.py
soilmoisture/tests/test_integration.py
soilmoisture/tests/test_lprm_utils.py
soilmoisture/tests/test_matching.py
soilmoisture/tests/test_ml.py
soilmoisture/tests/test_parameters.py
soilmoisture/tests/test_time_utils.py
soilmoisture/tests/test_visualization.py
soilmoisture/utils/__init__.py
soilmoisture/utils/geo_utils.py
soilmoisture/utils/time_utils.py
soilmoisture/visualization/__init__.py
polerisk-1.1.0.dist-info/METADATA
polerisk-1.1.0.dist-info/WHEEL
polerisk-1.1.0.dist-info/top_level.txt
polerisk-1.1.0.dist-info/RECORD
