Metadata-Version: 2.4
Name: polerisk
Version: 1.1.0
Summary: Predictive utility pole failure analysis and maintenance optimization platform
Home-page: https://github.com/kylejones200/polerisk
Author: Kyle T. Jones
Author-email: "Kyle T. Jones" <kyletjones@gmail.com>
License: MIT
Project-URL: homepage, https://github.com/kylejones200/polerisk
Project-URL: documentation, https://polerisk.readthedocs.io/
Project-URL: bug-tracker, https://github.com/kylejones200/polerisk/issues
Project-URL: changelog, https://github.com/kylejones200/polerisk/blob/main/CHANGELOG.md
Classifier: Development Status :: 5 - Production/Stable
Classifier: Intended Audience :: Developers
Classifier: Intended Audience :: Science/Research
Classifier: License :: OSI Approved :: MIT License
Classifier: Programming Language :: Python :: 3.12
Classifier: Programming Language :: Python :: 3.13
Classifier: Topic :: Scientific/Engineering
Classifier: Topic :: Scientific/Engineering :: Information Analysis
Classifier: Topic :: Utilities
Requires-Python: >=3.12
License-File: LICENSE
Requires-Dist: numpy>=1.20.0
Requires-Dist: pandas>=1.3.0
Requires-Dist: matplotlib>=3.4.0
Requires-Dist: scipy>=1.7.0
Requires-Dist: netCDF4>=1.5.0
Requires-Dist: cartopy>=0.19.0
Requires-Dist: seaborn>=0.11.0
Requires-Dist: python-dateutil>=2.8.2
Requires-Dist: scikit-learn>=1.0.0
Requires-Dist: joblib>=1.0.0
Requires-Dist: jinja2>=3.0.0
Requires-Dist: signalplot>=0.1.2
Requires-Dist: folium>=0.12.0
Provides-Extra: performance
Requires-Dist: numba>=0.56.0; extra == "performance"
Provides-Extra: dev
Requires-Dist: pytest>=6.0.0; extra == "dev"
Requires-Dist: pytest-cov>=2.0.0; extra == "dev"
Requires-Dist: pytest-benchmark>=3.4.0; extra == "dev"
Requires-Dist: hypothesis>=6.0.0; extra == "dev"
Requires-Dist: black>=21.7b0; extra == "dev"
Requires-Dist: isort>=5.0.0; extra == "dev"
Requires-Dist: flake8>=3.9.0; extra == "dev"
Requires-Dist: mypy>=0.910; extra == "dev"
Provides-Extra: docs
Requires-Dist: sphinx>=4.0.0; extra == "docs"
Requires-Dist: sphinx-rtd-theme>=0.5.0; extra == "docs"
Requires-Dist: myst-parser>=0.17.0; extra == "docs"
Provides-Extra: ml
Requires-Dist: tensorflow>=2.8.0; extra == "ml"
Requires-Dist: torch>=1.10.0; extra == "ml"
Requires-Dist: xgboost>=1.5.0; extra == "ml"
Provides-Extra: web
Requires-Dist: flask>=2.0.0; extra == "web"
Requires-Dist: flask-cors>=3.0.0; extra == "web"
Requires-Dist: fastapi>=0.70.0; extra == "web"
Requires-Dist: uvicorn[standard]>=0.15.0; extra == "web"
Requires-Dist: gunicorn>=20.1.0; extra == "web"
Provides-Extra: cloud
Requires-Dist: boto3>=1.20.0; extra == "cloud"
Requires-Dist: docker>=5.0.0; extra == "cloud"
Requires-Dist: dask>=2021.10.0; extra == "cloud"
Provides-Extra: all
Requires-Dist: numba>=0.56.0; extra == "all"
Requires-Dist: tensorflow>=2.8.0; extra == "all"
Requires-Dist: torch>=1.10.0; extra == "all"
Requires-Dist: xgboost>=1.5.0; extra == "all"
Requires-Dist: flask>=2.0.0; extra == "all"
Requires-Dist: flask-cors>=3.0.0; extra == "all"
Requires-Dist: fastapi>=0.70.0; extra == "all"
Requires-Dist: uvicorn[standard]>=0.15.0; extra == "all"
Requires-Dist: gunicorn>=20.1.0; extra == "all"
Requires-Dist: boto3>=1.20.0; extra == "all"
Requires-Dist: docker>=5.0.0; extra == "all"
Requires-Dist: dask>=2021.10.0; extra == "all"
Dynamic: author
Dynamic: home-page
Dynamic: license-file
Dynamic: requires-python
